[
  {
    "content": "Ne regarde pas l’escalier tout entier, commence simplement par la première marche.",
    "author": "Martin Luther King Jr."
  },
  {
    "content": "Ils ne savaient pas que c’était impossible, alors ils l’ont fait.",
    "author": "Mark Twain"
  },
  {
    "content": "Tu ne trouves pas le bonheur, tu le crées.",
    "author": "Camilla Eyring Kimball"
  },
  {
    "content": "Le courage n’est pas l’absence de peur, mais la capacité de la vaincre.",
    "author": "Nelson Mandela"
  },
  {
    "content": "Rêve grand, commence petit, agis maintenant.",
    "author": "Robin Sharma"
  },
  {
    "content": "Ce n’est pas la chance qui crée les opportunités, c’est la persévérance.",
    "author": "Anonyme"
  },
  {
    "content": "Fais chaque jour quelque chose qui te rapproche de ton futur idéal.",
    "author": "Anonyme"
  },
  {
    "content": "La discipline te mène là où la motivation seule ne suffit pas.",
    "author": "Anonyme"
  },
  {
    "content": "Chaque pas compte, même les plus petits.",
    "author": "Anonyme"
  },
  {
    "content": "Ta seule limite, c’est toi-même.",
    "author": "Anonyme"
  },
  {
    "content": "Le futur appartient à ceux qui croient à la beauté de leurs rêves.",
    "author": "Eleanor Roosevelt"
  },
  {
    "content": "Sois fier de la distance parcourue, même si le sommet est encore loin.",
    "author": "Anonyme"
  },
  {
    "content": "Transforme tes blessures en sagesse.",
    "author": "Oprah Winfrey"
  },
  {
    "content": "La constance bat le talent quand le talent n’est pas constant.",
    "author": "Anonyme"
  },
  {
    "content": "La vie est un mystère qu’il faut vivre, et non un problème à résoudre.",
    "author": "Gandhi"
  },
  {
    "content": "Le succès n’est pas la clé du bonheur. Le bonheur est la clé du succès.",
    "author": "Albert Schweitzer"
  },
  {
    "content": "Fais de ta vie un rêve, et d’un rêve, une réalité.",
    "author": "Antoine de Saint-Exupéry"
  },
  {
    "content": "C'est peut etre demain !",
    "author": "Gamze"
  }
]
